daily_event_logger/__init__.py
daily_event_logger/elog.py
daily_event_logger-0.1.4.dist-info/entry_points.txt
daily_event_logger-0.1.4.dist-info/LICENSE
daily_event_logger-0.1.4.dist-info/WHEEL
daily_event_logger-0.1.4.dist-info/METADATA
daily_event_logger-0.1.4.dist-info/RECORD
