Metadata-Version: 2.1
Name: daily-event-logger
Version: 0.1.4
Summary: A utility for logging daily tasks and events.
Home-page: https://github.com/hyperreal64/daily-event-logger
License: GPL-3.0-or-later
Author: Jeffrey Serio
Author-email: hyperreal@fedoraproject.org
Requires-Python: >=3.10,<4.0
Classifier: License :: OSI Approved :: GNU General Public License v3 or later (GPLv3+)
Classifier: Programming Language :: Python :: 3
Classifier: Programming Language :: Python :: 3.10
Requires-Dist: jsonschema (>=4.17.0,<5.0.0)
Requires-Dist: rich (>=12.6.0,<13.0.0)
Project-URL: Repository, https://github.com/hyperreal64/daily-event-logger
